aiohttpmap/__init__.py
aiohttpmap/aiohttpmap.py
aiohttpmap-0.2.0.dist-info/METADATA
aiohttpmap-0.2.0.dist-info/WHEEL
aiohttpmap-0.2.0.dist-info/top_level.txt
aiohttpmap-0.2.0.dist-info/RECORD
